odc/dscache/__init__.py
odc/dscache/_dscache.py
odc/dscache/_jsoncache.py
odc/dscache/_text.py
odc/dscache/_utils.py
odc/dscache/_version.py
odc/dscache/apps/__init__.py
odc/dscache/apps/dstiler.py
odc/dscache/apps/slurpy.py
odc/dscache/tools/__init__.py
odc/dscache/tools/_index.py
odc/dscache/tools/profiling.py
odc/dscache/tools/tiling.py
odc_dscache-1.9.1.dist-info/licenses/LICENSE
odc_dscache-1.9.1.dist-info/METADATA
odc_dscache-1.9.1.dist-info/WHEEL
odc_dscache-1.9.1.dist-info/entry_points.txt
odc_dscache-1.9.1.dist-info/top_level.txt
odc_dscache-1.9.1.dist-info/RECORD
