Metadata-Version: 2.4
Name: odc-dscache
Version: 1.9.1
Summary: ODC Dataset File Cache
Home-page: https://github.com/opendatacube/odc-dscache/
Author: Open Data Cube
Author-email: 
Maintainer: Open Data Cube
Maintainer-email: 
License: Apache License 2.0
Platform: any
Requires-Python: >=3.10
License-File: LICENSE
Requires-Dist: datacube>=1.9
Requires-Dist: pandas
Requires-Dist: psycopg2
Requires-Dist: zstandard
Requires-Dist: lmdb
Requires-Dist: click
Requires-Dist: toolz
Requires-Dist: odc-geo
Dynamic: license-file
